{
  "package": "dhcd",
  "module": "hotel",
  "description": "Permission route by group",
  "details": [
    {
      "name": "Quản lý khách sạn",
      "groups": [
        {
          "name": "View list",
          "routes": [
            "dhcd.hotel.manage",
            "dhcd.hotel.data",
            "dhcd.hotel.detail"
          ]
        },
        {
          "name": "Create",
          "routes": [
            "dhcd.hotel.create",
            "dhcd.hotel.add"
          ]
        },
        {
          "name": "Update",
          "routes": [
            "dhcd.hotel.show",
            "dhcd.hotel.update"
          ]
        },
        {
          "name": "Delete",
          "routes": [
            "dhcd.hotel.delete",
            "dhcd.hotel.confirm-delete"
          ]
        }
      ]
    }
  ]
}
